README.md
setup.py
cli/__init__.py
cli/triage.py
cli/tui.py
hatching_triage.egg-info/PKG-INFO
hatching_triage.egg-info/SOURCES.txt
hatching_triage.egg-info/dependency_links.txt
hatching_triage.egg-info/entry_points.txt
hatching_triage.egg-info/requires.txt
hatching_triage.egg-info/top_level.txt
triage/__init__.py
triage/__version__.py
triage/client.py
triage/pagination.py