Metadata-Version: 2.1
Name: hatching-triage
Version: 0.2.0
Summary: API client and CLI for Hatching Triage
Home-page: https://hatching.io/
Author: Hatching B.V.
Author-email: info@hatching.io
Requires-Python: >=3.6
